setup.py
python_banyan/examples/clock/__init__.py
python_banyan/examples/clock/binary_clock.py
python_banyan/examples/clock/clock_gui.py
python_banyan/examples/clock/tick_counter.py
python_banyan/examples/clock/tick_generator.py
python_banyan/examples/digital_toggling/__init__.py
python_banyan/examples/digital_toggling/arduino_digital_out.py
python_banyan/examples/digital_toggling/arduino_digital_out_aio.py
python_banyan/examples/digital_toggling/rpi_digital_out.py
python_banyan/examples/digital_toggling/toggler.py
python_banyan/examples/launching/__init__.py
python_banyan/examples/launching/lunch_clock.txt
python_banyan/examples/launching/lunch_config.py
python_banyan/examples/launching/lunch_redbot.txt
python_banyan/examples/matrix/__init__.py
python_banyan/examples/matrix/i2c_htk1633.py
python_banyan/examples/matrix/matrix_demo.py
python_banyan/examples/matrix/matrix_demo2.py
python_banyan/examples/raspberry_redbot/buzzer/__init__.py
python_banyan/examples/raspberry_redbot/buzzer/buzzer_pigpio.py
python_banyan/examples/raspberry_redbot/buzzer/validators/__init__.py
python_banyan/examples/raspberry_redbot/buzzer/validators/buzzer_test_driver.py
python_banyan/examples/raspberry_redbot/encoders/__init__.py
python_banyan/examples/raspberry_redbot/encoders/encoders_pigpio.py
python_banyan/examples/raspberry_redbot/encoders/validators/__init__.py
python_banyan/examples/raspberry_redbot/encoders/validators/generate_data_for_gui.py
python_banyan/examples/raspberry_redbot/gui/__init__.py
python_banyan/examples/raspberry_redbot/gui/redbot_controller.py
python_banyan/examples/raspberry_redbot/gui/redbot_controller_non_modified.py
python_banyan/examples/raspberry_redbot/i2c/__init__.py
python_banyan/examples/raspberry_redbot/i2c/i2c_pigpio.py
python_banyan/examples/raspberry_redbot/i2c/a2d/__init__.py
python_banyan/examples/raspberry_redbot/i2c/a2d/i2c_pcf8591.py
python_banyan/examples/raspberry_redbot/i2c/accelerometers/__init__.py
python_banyan_examples.egg-info/PKG-INFO
python_banyan_examples.egg-info/SOURCES.txt
python_banyan_examples.egg-info/dependency_links.txt
python_banyan_examples.egg-info/entry_points.txt
python_banyan_examples.egg-info/requires.txt
python_banyan_examples.egg-info/top_level.txt