Metadata-Version: 1.1
Name: python-banyan-examples
Version: 1.0
Summary: A Non-Blocking Event Driven Robotics Framework
Home-page: https://github.com/MrYsLab/python_banyan
Author: Alan Yorinks
Author-email: MisterYsLab@gmail.com
License: GNU General Public License v3 (GPLv3)
Keywords: python banyan,Raspberry Pi,ZeroMQ,MessagePack,RedBot
Platform: UNKNOWN
Classifier: Development Status :: 5 - Production/Stable
Classifier: Environment :: Other Environment
Classifier: Intended Audience :: Education
Classifier: Intended Audience :: Developers
Classifier: License :: OSI Approved :: GNU General Public License v3 or later (GPLv3+)
Classifier: Operating System :: OS Independent
Classifier: Programming Language :: Python :: 3.4
Classifier: Programming Language :: Python :: 3.5
Classifier: Topic :: Education
Classifier: Topic :: Software Development
Classifier: Topic :: Software Development :: Libraries :: Application Frameworks
Classifier: Topic :: System :: Hardware
